odoo/addons/l10n_es_aeat_mod303_oss/README.rst
odoo/addons/l10n_es_aeat_mod303_oss/__init__.py
odoo/addons/l10n_es_aeat_mod303_oss/__manifest__.py
odoo/addons/l10n_es_aeat_mod303_oss/data/2024-10/l10n.es.aeat.map.tax.line.csv
odoo/addons/l10n_es_aeat_mod303_oss/i18n/ca.po
odoo/addons/l10n_es_aeat_mod303_oss/i18n/ca_ES.po
odoo/addons/l10n_es_aeat_mod303_oss/i18n/es.po
odoo/addons/l10n_es_aeat_mod303_oss/i18n/l10n_es_aeat_mod303_oss.pot
odoo/addons/l10n_es_aeat_mod303_oss/models/__init__.py
odoo/addons/l10n_es_aeat_mod303_oss/models/l10n_es_aeat_map_tax_line.py
odoo/addons/l10n_es_aeat_mod303_oss/models/mod303.py
odoo/addons/l10n_es_aeat_mod303_oss/readme/CONTRIBUTORS.md
odoo/addons/l10n_es_aeat_mod303_oss/readme/DESCRIPTION.md
odoo/addons/l10n_es_aeat_mod303_oss/static/description/icon.png
odoo/addons/l10n_es_aeat_mod303_oss/static/description/icon_source.svg
odoo/addons/l10n_es_aeat_mod303_oss/static/description/index.html
odoo/addons/l10n_es_aeat_mod303_oss/tests/__init__.py
odoo/addons/l10n_es_aeat_mod303_oss/tests/test_l10n_es_aeat_mod303_oss.py
odoo_addon_l10n_es_aeat_mod303_oss-18.0.1.0.0.2.dist-info/METADATA
odoo_addon_l10n_es_aeat_mod303_oss-18.0.1.0.0.2.dist-info/WHEEL
odoo_addon_l10n_es_aeat_mod303_oss-18.0.1.0.0.2.dist-info/top_level.txt
odoo_addon_l10n_es_aeat_mod303_oss-18.0.1.0.0.2.dist-info/RECORD
